vrplib/__init__.py
vrplib/parse/__init__.py
vrplib/parse/distances/__init__.py
vrplib/parse/parse_distances.py
vrplib/parse/parse_solomon.py
vrplib/parse/parse_solution.py
vrplib/parse/parse_utils.py
vrplib/parse/parse_vrplib.py
vrplib/read/__init__.py
vrplib/read/read_instance.py
vrplib/read/read_solution.py
vrplib/write/__init__.py
vrplib/write/write_instance.py
vrplib/write/write_solution.py
vrplib-2.0.2.dist-info/licenses/LICENSE.md
vrplib-2.0.2.dist-info/WHEEL
vrplib-2.0.2.dist-info/METADATA
vrplib-2.0.2.dist-info/RECORD
