Metadata-Version: 2.4
Name: vrplib
Version: 2.0.2
Summary: Python library for reading and writing VRP instances.
Keywords: vehicle routing problem,benchmarking
Author: Leon Lan
Author-email: Leon Lan <leon.lanyidong@gmail.com>
License-Expression: MIT
License-File: LICENSE.md
Classifier: Intended Audience :: Developers
Classifier: Intended Audience :: Science/Research
Classifier: Development Status :: 5 - Production/Stable
Classifier: Topic :: Software Development
Classifier: Topic :: Scientific/Engineering
Classifier: Programming Language :: Python :: 3
Requires-Dist: numpy>=1.19.3 ; python_full_version < '3.12'
Requires-Dist: numpy>=1.26.0 ; python_full_version >= '3.12'
Requires-Python: >=3.10
Project-URL: issues, https://github.com/PyVRP/VRPLIB/issues
Project-URL: source, https://github.com/PyVRP/VRPLIB
